ccflow_rest/__init__.py
ccflow_rest/tests/test_all.py
ccflow_rest-0.1.0.dist-info/METADATA
ccflow_rest-0.1.0.dist-info/WHEEL
ccflow_rest-0.1.0.dist-info/licenses/LICENSE
ccflow_rest-0.1.0.dist-info/RECORD
